<?xml version="1.0"?>
<!DOCTYPE hibernate-mapping PUBLIC "-//Hibernate/Hibernate Mapping DTD 3.0//EN"
"http://hibernate.sourceforge.net/hibernate-mapping-3.0.dtd">
<!-- Generated 2018-2-25 0:56:38 by Hibernate Tools 3.5.0.Final -->
<hibernate-mapping>
    <class name="com.bsp.entity.News" table="news">
        <id name="nId" type="int" access="field">
            <column name="nId" />
            <generator class="native" />
        </id>
        <property name="nContent" type="text" access="field">
            <column name="nContent" not-null="true"/>
        </property>
        <property name="nStatus" type="byte" access="field">
            <column name="nStatus" not-null="true"/>
        </property>
        
        <many-to-one name="user" class="com.bsp.entity.User" fetch="join">
            <column name="UUID" not-null="true" length="33"/>
        </many-to-one>
    </class>
</hibernate-mapping>
